LoginRadius/__init__.py
LoginRadius/exceptions.py
LoginRadius/api/__init__.py
LoginRadius/api/account/__init__.py
LoginRadius/api/account/account_api.py
LoginRadius/api/account/role_api.py
LoginRadius/api/account/sott_api.py
LoginRadius/api/advanced/__init__.py
LoginRadius/api/advanced/configuration_api.py
LoginRadius/api/advanced/consentmanagement_api.py
LoginRadius/api/advanced/customobject_api.py
LoginRadius/api/advanced/multifactorauthentication_api.py
LoginRadius/api/advanced/reauthentication_api.py
LoginRadius/api/advanced/webhook_api.py
LoginRadius/api/authentication/__init__.py
LoginRadius/api/authentication/authentication_api.py
LoginRadius/api/authentication/onetouchlogin_api.py
LoginRadius/api/authentication/passwordlesslogin_api.py
LoginRadius/api/authentication/phoneauthentication_api.py
LoginRadius/api/authentication/pinauthentication_api.py
LoginRadius/api/authentication/riskbasedauthentication_api.py
LoginRadius/api/authentication/slidingtoken_api.py
LoginRadius/api/authentication/smartlogin_api.py
LoginRadius/api/social/__init__.py
LoginRadius/api/social/nativesocial_api.py
LoginRadius/api/social/social_api.py
loginradius_v2-11.7.0.dist-info/METADATA
loginradius_v2-11.7.0.dist-info/WHEEL
loginradius_v2-11.7.0.dist-info/top_level.txt
loginradius_v2-11.7.0.dist-info/RECORD
