Metadata-Version: 2.4
Name: LoginRadius-v2
Version: 11.7.0
Summary: Customer identity and access management for Python.
Home-page: https://loginradius.com/
Author: LoginRadius
Author-email: developers@loginradius.com
Classifier: Programming Language :: Python
Classifier: Programming Language :: Python :: 2.7
Classifier: Operating System :: OS Independent
Classifier: License :: OSI Approved :: MIT License
Classifier: Development Status :: 5 - Production/Stable
Classifier: Intended Audience :: Developers
Classifier: Topic :: Internet
Classifier: Topic :: Internet :: WWW/HTTP
Classifier: Topic :: Software Development :: Libraries :: Python Modules
Requires-Dist: urllib3
Requires-Dist: requests
Requires-Dist: cryptography
Requires-Dist: pbkdf2
Requires-Dist: flask
Dynamic: author
Dynamic: author-email
Dynamic: classifier
Dynamic: description
Dynamic: description-content-type
Dynamic: home-page
Dynamic: requires-dist
Dynamic: summary
